MANIFEST.in
requirements.txt
setup.py
slthlib/__init__.py
slthlib.egg-info/PKG-INFO
slthlib.egg-info/SOURCES.txt
slthlib.egg-info/dependency_links.txt
slthlib.egg-info/requires.txt
slthlib.egg-info/top_level.txt
slthlib/static/css/fontawesome.min.css
slthlib/static/css/leaflet-1.9.4.css
slthlib/static/css/solid.min.css
slthlib/static/css/style.css
slthlib/static/css/fonts/.DS_Store
slthlib/static/css/fonts/fa-solid-900.woff2
slthlib/static/css/fonts/rawline-400.woff
slthlib/static/css/fonts/rawline-500i.woff
slthlib/static/css/fonts/rawline-700.woff
slthlib/static/fonts/MicrosoftSansSerif.ttf
slthlib/static/fonts/MicrosoftSansSerifBold.ttf
slthlib/static/images/.DS_Store
slthlib/static/images/icp-brasil.png
slthlib/static/images/logo.png
slthlib/static/images/logo.svg
slthlib/static/images/user.svg
slthlib/static/js/default-passive-events.min.js
slthlib/static/js/echarts.min.js
slthlib/static/js/jitsi.min.js
slthlib/static/js/leaflet-1.9.4.js
slthlib/static/js/peerjs.min.js
slthlib/static/js/qrcode.min.js
slthlib/static/js/react-trigger-change.js
slthlib/static/js/vanilla-masker.min.js