Metadata-Version: 2.1
Name: slthlib
Version: 0.2.0
Summary: Libs for slth.
Home-page: https://github.com/brenokcc
Author: Breno Silva
Author-email: brenokcc@yahoo.com.br
License: BSD License
Classifier: Environment :: Web Environment
Classifier: Framework :: Django
Classifier: Intended Audience :: Developers
Classifier: License :: OSI Approved :: BSD License
Classifier: Operating System :: OS Independent
Classifier: Programming Language :: Python
Classifier: Topic :: Internet :: WWW/HTTP
Classifier: Topic :: Internet :: WWW/HTTP :: Dynamic Content
Requires-Dist: Django==5.1.3
Requires-Dist: selenium==4.26.1
Requires-Dist: whitenoise==6.8.2
Requires-Dist: pyyaml==6.0.2
Requires-Dist: Pillow==12.0.0
Requires-Dist: pywebpush==2.0.3
Requires-Dist: psycopg2-binary==2.9.10
Requires-Dist: django-redis==5.4.0
Requires-Dist: gunicorn==23.0.0
Requires-Dist: qrcode==8.0
Requires-Dist: pytz==2024.2
Requires-Dist: fpdf2==2.8.1
Requires-Dist: XlsxWriter==3.2.2
